pythonfinder/__init__.py
pythonfinder/cli.py
pythonfinder/environment.py
pythonfinder/exceptions.py
pythonfinder/main.py
pythonfinder/pythonfinder.py
pythonfinder/finders/__init__.py
pythonfinder/finders/asdf_finder.py
pythonfinder/finders/base_finder.py
pythonfinder/finders/path_finder.py
pythonfinder/finders/py_launcher_finder.py
pythonfinder/finders/pyenv_finder.py
pythonfinder/finders/system_finder.py
pythonfinder/finders/windows_registry.py
pythonfinder/models/__init__.py
pythonfinder/models/python_info.py
pythonfinder/utils/__init__.py
pythonfinder/utils/path_utils.py
pythonfinder/utils/version_utils.py
pythonfinder-3.0.0.dist-info/licenses/LICENSE.txt
pythonfinder-3.0.0.dist-info/METADATA
pythonfinder-3.0.0.dist-info/WHEEL
pythonfinder-3.0.0.dist-info/entry_points.txt
pythonfinder-3.0.0.dist-info/top_level.txt
pythonfinder-3.0.0.dist-info/zip-safe
pythonfinder-3.0.0.dist-info/RECORD
