Metadata-Version: 2.4
Name: pythonfinder
Version: 3.0.0
Summary: A cross-platform python discovery tool to help locate python on any system.
Author-email: Dan Ryan <dan@danryan.co>
License: MIT
Project-URL: Homepage, https://github.com/sarugaku/pythonfinder
Keywords: pythonfinder,path,finder,pathfinder,which,pep514,pyenv
Classifier: Development Status :: 5 - Production/Stable
Classifier: Intended Audience :: Developers
Classifier: License :: OSI Approved :: MIT License
Classifier: Operating System :: OS Independent
Classifier: Programming Language :: Python :: 3.8
Classifier: Programming Language :: Python :: 3.9
Classifier: Programming Language :: Python :: 3.10
Classifier: Programming Language :: Python :: 3.11
Classifier: Programming Language :: Python :: 3.12
Classifier: Programming Language :: Python :: 3.13
Classifier: Topic :: Software Development :: Build Tools
Classifier: Topic :: Software Development :: Libraries :: Python Modules
Classifier: Topic :: Utilities
Requires-Python: >=3.8
License-File: LICENSE.txt
Requires-Dist: packaging>=22.0
Provides-Extra: cli
Requires-Dist: click; extra == "cli"
Requires-Dist: colorama; extra == "cli"
Provides-Extra: tests
Requires-Dist: pytest; extra == "tests"
Requires-Dist: pytest-timeout; extra == "tests"
Requires-Dist: coverage[toml]; extra == "tests"
Provides-Extra: dev
Requires-Dist: parver; extra == "dev"
Requires-Dist: build; extra == "dev"
Requires-Dist: invoke; extra == "dev"
Requires-Dist: twine; extra == "dev"
Requires-Dist: lxml; extra == "dev"
Requires-Dist: pre-commit; extra == "dev"
Requires-Dist: towncrier; extra == "dev"
Dynamic: license-file
